entityrdfizer/__init__.py
entityrdfizer/app.py
entityrdfizer/driver.py
entityrdfizer/aboxgenerator/ABoxGeneration.py
entityrdfizer/aboxgenerator/ABoxTemplateCSVFileToRDF.py
entityrdfizer/aboxgenerator/ABoxTemplateCSVFilesToRDF.py
entityrdfizer/aboxgenerator/PropertyReader.py
entityrdfizer/aboxgenerator/__init__.py
entityrdfizer/aboxgenerator/csv2abox.py
entityrdfizer/aboxgenerator/tboxtools.py
entityrdfizer/conf/EntityRDFizer.properties
entityrdfizer/javagateway/__init__.py
entityrdfizer/javagateway/gateway.py
entityrdfizer/tboxgenerator/__init__.py
entityrdfizer/tboxgenerator/csv2tbox.py
entityrdfizer-1.0.7.dist-info/LICENSE
entityrdfizer-1.0.7.dist-info/METADATA
entityrdfizer-1.0.7.dist-info/WHEEL
entityrdfizer-1.0.7.dist-info/entry_points.txt
entityrdfizer-1.0.7.dist-info/top_level.txt
entityrdfizer-1.0.7.dist-info/RECORD
