Metadata-Version: 2.1
Name: entityrdfizer
Version: 1.0.7
Summary: Converts instances from a CSV file into RDF.
Home-page: https://github.com/cambridge-cares/TheWorldAvatar/tree/develop/EntityRDFizer
Author: Feroz Farazi
License: MIT
Platform: UNKNOWN
Requires-Python: >=3.5, <4
Requires-Dist: docopt
Requires-Dist: py4jps >=1.0.6
Requires-Dist: rdflib <6.0,>=4.2
